my_example_module/__init__.py
my_example_module/my_module.py
my_example_module/run.py
my_example_app-0.5.dist-info/METADATA
my_example_app-0.5.dist-info/WHEEL
my_example_app-0.5.dist-info/top_level.txt
my_example_app-0.5.dist-info/RECORD
