Metadata-Version: 2.1
Name: my_example_app
Version: 0.5
Summary: An example Python package
Home-page: UNKNOWN
Author: Your Name
Author-email: youremail@example.com
License: UNKNOWN
Platform: UNKNOWN
